sschema/__init__.py
sschema/handler/__init__.py
sschema/handler/sschema.py
sschema/schema/endian.yaml
sschema/schema/raw-unit.yaml
sschema/schema/si-unit.yaml
sschema/schema/type.yaml
sschema/schema/uuid.yaml
sschema-0.1.6.dist-info/LICENSE
sschema-0.1.6.dist-info/METADATA
sschema-0.1.6.dist-info/WHEEL
sschema-0.1.6.dist-info/top_level.txt
sschema-0.1.6.dist-info/RECORD
